mongodbautomation/__init__.py
mongodbautomation/mongo_crud.py
mongodbautomation_ravi-0.0.5.dist-info/METADATA
mongodbautomation_ravi-0.0.5.dist-info/WHEEL
mongodbautomation_ravi-0.0.5.dist-info/top_level.txt
mongodbautomation_ravi-0.0.5.dist-info/RECORD
